<bibdata type="standard">
  <title type="title-main" format="text/plain">IEEE Standard for Information Technology POSIX(R)-Based Supercomputing Application Environment Profile</title>
  <title type="main" format="text/plain">IEEE Standard for Information Technology POSIX(R)-Based Supercomputing Application Environment Profile</title>
  <uri type="src">https://ieeexplore.ieee.org/document/478420</uri>
  <docidentifier type="IEEE">IEEE Std 1003.10-1995</docidentifier>
  <docidentifier type="ISBN">978-0-7381-2761-3</docidentifier>
  <docidentifier type="DOI">10.1109/IEEESTD.1995.79371</docidentifier>
  <docnumber>1003.10-1995</docnumber>
  <date type="created">
    <on>1995-12-08</on>
  </date>
  <date type="published">
    <on>2019-04-24</on>
  </date>
  <date type="issued">
    <on>1995-06-14</on>
  </date>
  <contributor>
    <role type="publisher"/>
    <organization>
      <name>Institute of Electrical and Electronics Engineers</name>
      <abbreviation>IEEE</abbreviation>
      <uri>http://www.ieee.org</uri>
      <address>
        <city>New York</city>
        <country>USA</country>
      </address>
    </organization>
  </contributor>
  <language>en</language>
  <script>Latn</script>
  <abstract format="text/plain" language="en" script="Latn">This standard is related to the POSIX¨ series of standards for applications and user interfaces to open systems. It specifies the set of standards and the requirements needed for portability of supercomputing applications, users, and system administrators.</abstract>
  <copyright>
    <from>1995</from>
    <owner>
      <organization>
        <name>Institute of Electrical and Electronics Engineers</name>
        <abbreviation>IEEE</abbreviation>
        <uri>http://www.ieee.org</uri>
      </organization>
    </owner>
  </copyright>
  <keyword>IEEE standards</keyword>
  <keyword>AEP</keyword>
  <keyword>application portability</keyword>
  <keyword>batch</keyword>
  <keyword>portable application</keyword>
  <keyword>profile</keyword>
  <keyword>queue</keyword>
  <keyword>resource</keyword>
  <keyword>supercomputer</keyword>
  <keyword>supercomputing</keyword>
  <keyword>user portability</keyword>
</bibdata>