<bibdata type="standard">
  <title type="title-intro" format="text/plain">IEEE Guide for the Design, Construction, and Operation of Electric Power Substations for Community Acceptance and Environmental Compatibility</title>
  <title type="title-main" format="text/plain">Redline</title>
  <title type="main" format="text/plain">IEEE Guide for the Design, Construction, and Operation of Electric Power Substations for Community Acceptance and Environmental Compatibility - Redline</title>
  <uri type="src">https://ieeexplore.ieee.org/document/7021881</uri>
  <docidentifier type="IEEE">IEEE Std 1127-2013 (Revision of IEEE Std 1127-1998) - Redline</docidentifier>
  <docidentifier type="ISBN">978-0-7381-9525-4</docidentifier>
  <docnumber>1127-2013</docnumber>
  <date type="created">
    <on>2014-01-24</on>
  </date>
  <date type="published">
    <on>2015-01-26</on>
  </date>
  <date type="issued">
    <on>2013-12-11</on>
  </date>
  <contributor>
    <role type="publisher"/>
    <organization>
      <name>Institute of Electrical and Electronics Engineers</name>
      <abbreviation>IEEE</abbreviation>
      <uri>http://www.ieee.org</uri>
      <address>
        <city>New York</city>
        <country>USA</country>
      </address>
    </organization>
  </contributor>
  <language>en</language>
  <script>Latn</script>
  <abstract format="text/plain" language="en" script="Latn">Significant community acceptance and environmental compatibility items to be considered during the planning and design phases, the construction period, and the operation of electric supply substations are identified, and ways to address these concerns to obtain community acceptance and environmental compatibility are documented. On-site generation and telecommunication facilities are not considered.</abstract>
  <copyright>
    <from>2014</from>
    <owner>
      <organization>
        <name>Institute of Electrical and Electronics Engineers</name>
        <abbreviation>IEEE</abbreviation>
        <uri>http://www.ieee.org</uri>
      </organization>
    </owner>
  </copyright>
  <relation type="updates">
    <description format="text/plain" language="en" script="Latn">revises</description>
    <bibitem>
      <formattedref format="text/plain">IEEE Std 1127-1998</formattedref>
    </bibitem>
  </relation>
  <keyword>IEEE standards</keyword>
  <keyword>Substations</keyword>
  <keyword>Communities</keyword>
  <keyword>Industrial plants</keyword>
  <keyword>Wetlands</keyword>
  <keyword>Hazardous areas</keyword>
  <keyword>Environmental factors</keyword>
  <keyword>Electric power stations</keyword>
  <keyword>Construction</keyword>
  <keyword>A-weighted sound level</keyword>
  <keyword>commercial zone</keyword>
  <keyword>community involvement</keyword>
  <keyword>hazardous material</keyword>
  <keyword>IEEE 1127(TM)</keyword>
  <keyword>industrial zone</keyword>
  <keyword>noise</keyword>
  <keyword>permitting process</keyword>
  <keyword>residential zone</keyword>
  <keyword>wetlands</keyword>
</bibdata>