<bibdata type="standard">
  <title type="title-main" format="text/plain">IEEE Standard Definitions of Terms for Antennas</title>
  <title type="main" format="text/plain">IEEE Standard Definitions of Terms for Antennas</title>
  <uri type="src">https://ieeexplore.ieee.org/document/7366738</uri>
  <docidentifier type="IEEE">IEEE No 145-1973</docidentifier>
  <docidentifier type="ISBN">978-1-5044-0165-4</docidentifier>
  <docidentifier type="DOI">10.1109/IEEESTD.1973.7366738</docidentifier>
  <docnumber>145-1973</docnumber>
  <date type="created">
    <on>1973-08-02</on>
  </date>
  <date type="published">
    <on>2015-12-28</on>
  </date>
  <date type="issued">
    <on>1972-09-20</on>
  </date>
  <contributor>
    <role type="publisher"/>
    <organization>
      <name>Institute of Electrical and Electronics Engineers</name>
      <abbreviation>IEEE</abbreviation>
      <uri>http://www.ieee.org</uri>
      <address>
        <city>New York</city>
        <country>USA</country>
      </address>
    </organization>
  </contributor>
  <language>en</language>
  <script>Latn</script>
  <abstract format="text/plain" language="en" script="Latn">In 1969, IEEE Standard 145 was published as a list of basic terms of antenna theory and practice. That document treated antenna gain as a fundamental property, with impedance and polarization as independent properties. The definitions of gain, directivity, impedance, and polarization were worded to emphasize this independence. Various other significant groups of terms were also defined, such as the regions of the electromagnetic field of an antenna, the terms relating to cross section, the tracking antenna techniques, and the idealized radiators.</abstract>
  <copyright>
    <from>1973</from>
    <owner>
      <organization>
        <name>Institute of Electrical and Electronics Engineers</name>
        <abbreviation>IEEE</abbreviation>
        <uri>http://www.ieee.org</uri>
      </organization>
    </owner>
  </copyright>
  <keyword>Dictionaries</keyword>
  <keyword>Antennas</keyword>
  <keyword>Terminology</keyword>
</bibdata>