<bibdata type="standard">
  <title type="title-main" format="text/plain">AIEE Standards for Apparatus Bushings and Proposed Test Code for Apparatus Bushings</title>
  <title type="main" format="text/plain">AIEE Standards for Apparatus Bushings and Proposed Test Code for Apparatus Bushings</title>
  <uri type="src">https://ieeexplore.ieee.org/document/7370867</uri>
  <docidentifier type="IEEE">AIEE No 21-1942</docidentifier>
  <docidentifier type="ISBN">978-1-5044-0205-7</docidentifier>
  <docidentifier type="DOI">10.1109/IEEESTD.1942.7370867</docidentifier>
  <docnumber>21-1942</docnumber>
  <date type="updated">
    <on>2016-02-26</on>
  </date>
  <date type="created">
    <on>1942-05-31</on>
  </date>
  <date type="published">
    <on>2016-01-04</on>
  </date>
  <date type="issued">
    <on>1942</on>
  </date>
  <contributor>
    <role type="publisher"/>
    <organization>
      <name>Institute of Electrical and Electronics Engineers</name>
      <abbreviation>IEEE</abbreviation>
      <uri>http://www.ieee.org</uri>
      <address>
        <city/>
        <country>USA</country>
      </address>
    </organization>
  </contributor>
  <language>en</language>
  <script>Latn</script>
  <abstract format="text/plain" language="en" script="Latn">These standards specifically cover the following types of bushings (a) Outdoor bushings for large apparatus. (b) Cover type bushings for small apparatus. (c) Indoor bushings for all types of apparatus except dry type instrument transformers, air-blast transformers, dry type regulators, and circuit breakers rated below 5,000 volts, and non-oiltight oil circuit breakers rated 50,000 kva or less. These standards are not intended to apply to wall bushings, cable potheads, nor insulators for backconnected disconnecting switches, although many of the principles may be applicable. The bushing requirements as specified in these standards apply to bushings when mounted for testing in accordance with specified arrangements as given in the Test Code (Appendix I). Requirements when installed in apparatus should be covered by standards for such apparatus.</abstract>
  <copyright>
    <from>1942</from>
    <owner>
      <organization>
        <name>AIEE</name>
      </organization>
    </owner>
  </copyright>
  <keyword>AIEE Standards</keyword>
  <keyword>Apparatus Bushings</keyword>
  <keyword>Bushings</keyword>
  <keyword>Testing</keyword>
  <keyword>Service conditions</keyword>
</bibdata>