<bibdata type="standard">
  <title type="title-main" format="text/plain">AIEE Revised Report on Standards for Valve and Expulsion Type Lightning Arresters</title>
  <title type="main" format="text/plain">AIEE Revised Report on Standards for Valve and Expulsion Type Lightning Arresters</title>
  <uri type="src">https://ieeexplore.ieee.org/document/7404215</uri>
  <docidentifier type="IEEE">AIEE No 28B-1956</docidentifier>
  <docidentifier type="ISBN">978-1-5044-0272-9</docidentifier>
  <docidentifier type="DOI">10.1109/IEEESTD.1956.7404215</docidentifier>
  <docnumber>28B-1956</docnumber>
  <date type="created">
    <on>1956-02-29</on>
  </date>
  <date type="published">
    <on>2016-02-10</on>
  </date>
  <date type="issued">
    <on>1956</on>
  </date>
  <contributor>
    <role type="publisher"/>
    <organization>
      <name>Institute of Electrical and Electronics Engineers</name>
      <abbreviation>IEEE</abbreviation>
      <uri>http://www.ieee.org</uri>
      <address>
        <city>New York</city>
        <country>USA</country>
      </address>
    </organization>
  </contributor>
  <language>en</language>
  <script>Latn</script>
  <copyright>
    <from>1956</from>
    <owner>
      <organization>
        <name>AIEE</name>
      </organization>
    </owner>
  </copyright>
  <keyword>AIEE Standards</keyword>
  <keyword>Arresters</keyword>
  <keyword>Lightning</keyword>
  <keyword>Valves</keyword>
  <keyword>Surge protection</keyword>
  <keyword>Terminology</keyword>
</bibdata>