<bibdata type="standard">
  <title type="title-intro" format="text/plain">IEEE Recommended Practice for Establishing Liquid-Filled and Dry-Type Power and Distribution Transformer Capability When Supplying Nonsinusoidal Load Currents</title>
  <title type="title-main" format="text/plain">Redline</title>
  <title type="main" format="text/plain">IEEE Recommended Practice for Establishing Liquid-Filled and Dry-Type Power and Distribution Transformer Capability When Supplying Nonsinusoidal Load Currents - Redline</title>
  <uri type="src">https://ieeexplore.ieee.org/document/5985452</uri>
  <docidentifier type="IEEE">IEEE Std C57.110-2008 (Revision of IEEE Std C57.110-1998) - Redline</docidentifier>
  <docidentifier type="ISBN">978-0-7381-7021-3</docidentifier>
  <docnumber>C57.110-2008</docnumber>
  <date type="created">
    <on>2008-08-15</on>
  </date>
  <date type="published">
    <on>2013-08-15</on>
  </date>
  <date type="issued">
    <on>2008-03-27</on>
  </date>
  <contributor>
    <role type="publisher"/>
    <organization>
      <name>Institute of Electrical and Electronics Engineers</name>
      <abbreviation>IEEE</abbreviation>
      <uri>http://www.ieee.org</uri>
    </organization>
  </contributor>
  <language>en</language>
  <script>Latn</script>
  <abstract format="text/plain" language="en" script="Latn">This recommended practice provides calculation methods to conservatively evaluate the feasibility for an existing installed dry-type or liquid-filled transformer, to supply nonsinusoidal load currents as a portion of the total load. This recommended practice also provides necessary application information to assist in properly specifying a new transformer expected to carry a load, a portion of which is composed of nonsinusoidal load currents. A number of examples illustrating these methods and calculations are presented. Reference annexes provide a comparison of the document calculations to calculations found in other industry standards. Suggested temperature rise calculation methods are detailed for reference purposes.</abstract>
  <copyright>
    <from>2011</from>
    <owner>
      <organization>
        <name>Institute of Electrical and Electronics Engineers</name>
        <abbreviation>IEEE</abbreviation>
        <uri>http://www.ieee.org</uri>
      </organization>
    </owner>
  </copyright>
  <relation type="obsoletedBy">
    <bibitem>
      <formattedref format="text/plain">IEEE Std C57.110™-2018 (Revision of IEEE Std C57.110-2008)</formattedref>
    </bibitem>
  </relation>
  <relation type="obsoletedBy">
    <bibitem>
      <formattedref format="text/plain">IEEE Std C57.110™-2018 (Revision of IEEE Std C57.110-2008)</formattedref>
    </bibitem>
  </relation>
  <keyword>IEEE standards</keyword>
  <keyword>Transformers</keyword>
  <keyword>Voltage transformers</keyword>
  <keyword>Voltage control</keyword>
  <keyword>Windings</keyword>
  <keyword>C57.110-2008</keyword>
  <keyword>accuracy</keyword>
  <keyword>current transformer</keyword>
  <keyword>instrument transformer</keyword>
  <keyword>primary winding</keyword>
  <keyword>rated secondary voltage</keyword>
  <keyword>routine tests</keyword>
  <keyword>secondary winding</keyword>
  <keyword>type tests</keyword>
  <keyword>voltage transformer</keyword>
</bibdata>