<bibdata type="standard">
  <title type="title-intro" format="text/plain">IEEE Draft Standard</title>
  <title type="title-main" format="text/plain">Health Informatics</title>
  <title type="title-part" format="text/plain">Personal Health Device Communication -- Device Specialization -- Blood Pressure Monitor</title>
  <title type="main" format="text/plain">IEEE Draft Standard - Health Informatics - Personal Health Device Communication -- Device Specialization -- Blood Pressure Monitor</title>
  <uri type="src">https://ieeexplore.ieee.org/document/8799044</uri>
  <docidentifier type="IEEE">IEEE P11073-10407/D9, July 2019</docidentifier>
  <docidentifier type="ISBN">978-1-5044-6075-0</docidentifier>
  <docnumber>P11073-10407/D9, Jul 2019</docnumber>
  <date type="created">
    <on>2019-08-13</on>
  </date>
  <date type="published">
    <on>2019-08-14</on>
  </date>
  <date type="issued">
    <on>2020-01-30</on>
  </date>
  <contributor>
    <role type="publisher"/>
    <organization>
      <name>Institute of Electrical and Electronics Engineers</name>
      <abbreviation>IEEE</abbreviation>
      <uri>http://www.ieee.org</uri>
    </organization>
  </contributor>
  <language>en</language>
  <script>Latn</script>
  <abstract format="text/plain" language="en" script="Latn">Within the context of the ISO/IEEE 11073 family of standards for device communication, this standard establishes a normative definition of communication between personal telehealth blood pressure monitor devices and compute engines (e.g., cell phones, personal computers, personal health appliances, and set top boxes) in a manner that enables plug-and-play interoperability. It leverages appropriate portions of existing standards including ISO/IEEE 11073 terminology, information models, application profile standards, and transport standards. It specifies the use of specific term codes, formats, and behaviors in telehealth environments restricting optionality in base frameworks in favor of interoperability. This standard defines a common core of communication functionality for personal telehealth blood pressure monitors.</abstract>
  <copyright>
    <from>2019</from>
    <owner>
      <organization>
        <name>Institute of Electrical and Electronics Engineers</name>
        <abbreviation>IEEE</abbreviation>
        <uri>http://www.ieee.org</uri>
      </organization>
    </owner>
  </copyright>
  <relation type="updates">
    <description format="text/plain" language="en" script="Latn">revises</description>
    <bibitem>
      <formattedref format="text/plain">IEEE STD 11073-10407-2008</formattedref>
    </bibitem>
  </relation>
  <keyword>IEEE Standards</keyword>
  <keyword>Medical devices</keyword>
  <keyword>Biomedical monitoring</keyword>
  <keyword>Blood pressure measurement</keyword>
  <keyword>Bioinformatics</keyword>
  <keyword>blood pressure monitor</keyword>
  <keyword>IEEE 11073-10407</keyword>
  <keyword>medical device communication</keyword>
  <keyword>personal health devices</keyword>
</bibdata>