<bibdata type="standard">
  <title type="title-intro" format="text/plain">IEEE Draft Recommended Practice for Learning Technology</title>
  <title type="title-main" format="text/plain">IMS Content Packaging Information Model (CP) Version 1.2</title>
  <title type="title-part" format="text/plain">Mapping to the Conceptual Model for Resource Aggregation</title>
  <title type="main" format="text/plain">IEEE Draft Recommended Practice for Learning Technology - IMS Content Packaging Information Model (CP) Version 1.2 - Mapping to the Conceptual Model for Resource Aggregation</title>
  <uri type="src">https://ieeexplore.ieee.org/document/7270967</uri>
  <docidentifier type="IEEE">IEEE P1484.13.4/D3, August 2015</docidentifier>
  <docidentifier type="ISBN">978-0-7381-9966-5</docidentifier>
  <docnumber>P1484.13.4/D3, Aug 2015</docnumber>
  <date type="created">
    <on>2015-01-01</on>
  </date>
  <date type="published">
    <on>2015-09-17</on>
  </date>
  <date type="issued">
    <on>2015</on>
  </date>
  <contributor>
    <role type="publisher"/>
    <organization>
      <name>Institute of Electrical and Electronics Engineers</name>
      <abbreviation>IEEE</abbreviation>
      <uri>http://www.ieee.org</uri>
      <address>
        <city>Piscataway</city>
        <country>USA</country>
      </address>
    </organization>
  </contributor>
  <language>en</language>
  <script>Latn</script>
  <abstract format="text/plain" language="en" script="Latn">This recommended practice specifies how the elements and attributes defined in the IMS Content Packaging Information Model (CP) Version 1.2 relate to the components of the conceptual model for resource aggregation defined in IEEE Std 1484.13.1(TM)-2012.</abstract>
  <copyright>
    <from>2015</from>
    <owner>
      <organization>
        <name>Institute of Electrical and Electronics Engineers</name>
        <abbreviation>IEEE</abbreviation>
        <uri>http://www.ieee.org</uri>
      </organization>
    </owner>
  </copyright>
  <keyword>IEEE Standards</keyword>
  <keyword>Resource management</keyword>
  <keyword>Aggregation management</keyword>
  <keyword>Digital systems</keyword>
  <keyword>Learning technology</keyword>
  <keyword>Content management</keyword>
  <keyword>aggregation format</keyword>
  <keyword>conceptual model</keyword>
  <keyword>content aggregation</keyword>
  <keyword>digital aggregation</keyword>
  <keyword>digital resource</keyword>
  <keyword>IEEE 1484.13.6</keyword>
  <keyword>IMS Content Packaging Information Model</keyword>
  <keyword>IMS CP</keyword>
  <keyword>RAMLET</keyword>
  <keyword>resource aggregation</keyword>
  <keyword>resource aggregation format</keyword>
</bibdata>