<bibdata type="standard">
  <title type="title-main" format="text/plain">IEEE Draft Recommended Practice for Overvoltage and Insulation Coordination of Transmission Systems at 1000kV AC and Above</title>
  <title type="main" format="text/plain">IEEE Draft Recommended Practice for Overvoltage and Insulation Coordination of Transmission Systems at 1000kV AC and Above</title>
  <uri type="src">https://ieeexplore.ieee.org/document/6657675</uri>
  <docidentifier type="IEEE">IEEE P1862/D6-3, September 2013</docidentifier>
  <docidentifier type="ISBN">978-0-7381-8786-0</docidentifier>
  <docnumber>P1862/D6-3, Sept 2013</docnumber>
  <date type="created">
    <on>2013-11-07</on>
  </date>
  <date type="published">
    <on>2013-11-07</on>
  </date>
  <date type="issued">
    <on>2014-02-20</on>
  </date>
  <contributor>
    <role type="publisher"/>
    <organization>
      <name>Institute of Electrical and Electronics Engineers</name>
      <abbreviation>IEEE</abbreviation>
      <uri>http://www.ieee.org</uri>
      <address>
        <city>Piscataway</city>
        <country>USA</country>
      </address>
    </organization>
  </contributor>
  <language>en</language>
  <script>Latn</script>
  <abstract format="text/plain" language="en" script="Latn">This recommended practice specifies the procedure for selection of insulation levels of UHV AC transmission lines and substations. It also specifies reliability criterion under switching overvoltage and lightning overvoltage. It also suggests the calculation methods of insulation coordination design. According to the characteristics of UHV AC systems, overvoltages mitigation measures are recommended. Some examples of insulation coordination are presented.</abstract>
  <copyright>
    <from>2013</from>
    <owner>
      <organization>
        <name>Institute of Electrical and Electronics Engineers</name>
        <abbreviation>IEEE</abbreviation>
        <uri>http://www.ieee.org</uri>
      </organization>
    </owner>
  </copyright>
  <keyword>IEEE standards</keyword>
  <keyword>Voltage control</keyword>
  <keyword>Lightning</keyword>
  <keyword>Insulation testing</keyword>
  <keyword>High-voltage techniques</keyword>
  <keyword>Phase measurement</keyword>
  <keyword>Atmospheric measurements</keyword>
  <keyword>Ultra-high voltage(UHV)</keyword>
  <keyword>atmospheric correction factor</keyword>
  <keyword>basic lightning impulse insulation level (BIL)</keyword>
  <keyword>basic switching impulse insulation level (BSL)</keyword>
  <keyword>clearance</keyword>
  <keyword>crest value</keyword>
  <keyword>ground fault factor</keyword>
  <keyword>insulation coordination</keyword>
  <keyword>insulation design</keyword>
  <keyword>overvoltage</keyword>
  <keyword>phase-to-ground insulation configuration</keyword>
  <keyword>phase-to phase insulation configuration</keyword>
  <keyword>protective margin</keyword>
  <keyword>protective ratio</keyword>
  <keyword>shielding failures</keyword>
  <keyword>standard withstand voltages</keyword>
  <keyword>voltage stresses</keyword>
  <keyword>IEEE P1862</keyword>
</bibdata>